CHANGELOG.md
xproc/__init__.py
xproc/cgroups.py
xproc/console.py
xproc/interrupt.py
xproc/load.py
xproc/meminfo.py
xproc/pidstatus.py
xproc/slabinfo.py
xproc/stat.py
xproc/uptime.py
xproc/util.py
xproc/value.py
xproc/vmstat.py
xproc-1.4.1.dist-info/entry_points.txt
xproc-1.4.1.dist-info/LICENSE
xproc-1.4.1.dist-info/WHEEL
xproc-1.4.1.dist-info/METADATA
xproc-1.4.1.dist-info/RECORD
